load_simulator/__init__.py
load_simulator/constants.py
load_simulator/load_simulator.py
load_simulator/models.py
load_simulator/operation_executor.py
load_simulator/utilities.py
load_simulator-0.1.1.dist-info/LICENSE
load_simulator-0.1.1.dist-info/METADATA
load_simulator-0.1.1.dist-info/WHEEL
load_simulator-0.1.1.dist-info/RECORD
