Metadata-Version: 2.1
Name: load-simulator
Version: 0.1.1
Summary: A package to simulate operations load.
Author: Andrew Yourkin
Author-email: andrew@yourkin.io
Requires-Python: >=3.11,<4.0
Classifier: Programming Language :: Python :: 3
Classifier: Programming Language :: Python :: 3.11
Requires-Dist: pydantic (>=2.4.2,<3.0.0)
Requires-Dist: typer (>=0.9.0,<0.10.0)
